{
  "name": "URL ColorUP in textarea",
  "tagline": "jQuery URL ColorUP",
  "body": "jQuery URL ColorUP [![Build Status](https://travis-ci.org/amitmerchant1990/urlcolorup.png?branch=master)](https://travis-ci.org/amitmerchant1990/urlcolorup)\r\n===============\r\n\r\nThe plugin allows it to automatically highlight URLs in textareas like those on Twitter.\r\n\r\nPull requests are always welcomed if you find any bugs or you want to make it better.\r\n\r\nYou can find more information about this plugin below :\r\n\r\n<a href=\"http://amitmerchant1990.github.io/urlcolorup/\">Offcial Plugin Page</a>\r\n\r\nFind it on <a href=\"http://plugins.jquery.com/urlcolorup\" target=\"_blank\">jQuery Plugin Registry</a>\r\n\r\nOr\r\n\r\n<a href=\"http://www.jqueryscript.net/demo/Twitter-Like-URL-Highlighting-with-jQuery-urlcolorup-Plugin\" target=\"_blank\">Try demo!</a>\r\n\r\nUsage\r\n=====\r\n```javascript\r\n$(document).ready(function() {\r\n   $(\"textarea\").urlcolorup();\r\n});\r\n```\r\n\r\nInstall\r\n=======\r\n[![NPM](https://nodei.co/npm/jquery-url-colorup.png?downloads=true&downloadRank=true&stars=true)](https://nodei.co/npm/jquery-url-colorup/)\r\n\r\nWatch URL ColorUp in action\r\n===============\r\n\r\n![URL ColorUp](https://raw.githubusercontent.com/amitmerchant1990/urlcolorup/master/images/demo.gif)\r\n\r\nDonations\r\n=========\r\n<a href='https://pledgie.com/campaigns/29572'><img alt='Click here to lend your support to: jQuery URL ColorUP and make a donation at pledgie.com !' src='https://pledgie.com/campaigns/29572.png?skin_name=chrome' border='0' ></a>\r\n",
  "google": "UA-43339302-1",
  "note": "Don't delete this file! It's used internally to help with page regeneration."
}